pyaces/__init__.py
pyaces/aces.py
pyaces/compaces.py
pyaces-0.0.4.dist-info/LICENSE
pyaces-0.0.4.dist-info/METADATA
pyaces-0.0.4.dist-info/WHEEL
pyaces-0.0.4.dist-info/top_level.txt
pyaces-0.0.4.dist-info/RECORD
