Metadata-Version: 2.1
Name: pyaces
Version: 0.0.4
Summary: A python library for the fully homomorphic encryption scheme ACES
Home-page: https://github.com/remytuyeras/aces
Author: Remy Tuyeras
Author-email: Remy Tuyeras <rtuyeras@gmail.com>
License: MIT
Project-URL: Homepage, https://github.com/remytuyeras/aces
Project-URL: Issues, https://github.com/remytuyeras/aces/issues
Project-URL: repository, https://github.com/remytuyeras/aces
Keywords: ACES,PyACES
Classifier: Development Status :: 4 - Beta
Classifier: Intended Audience :: Developers
Classifier: Intended Audience :: Science/Research
Classifier: Topic :: Software Development :: Build Tools
Classifier: Programming Language :: Python :: 3
Classifier: Programming Language :: Python :: 3.9
Requires-Python: >=3.9
License-File: LICENSE
Requires-Dist: build
Requires-Dist: twine
Requires-Dist: numpy
